mcp_feedback_hall/__init__.py
mcp_feedback_hall/__main__.py
mcp_feedback_hall/debug.py
mcp_feedback_hall/i18n.py
mcp_feedback_hall/py.typed
mcp_feedback_hall/server.py
mcp_feedback_hall/desktop_app/__init__.py
mcp_feedback_hall/desktop_app/desktop_app.py
mcp_feedback_hall/desktop_release/__init__.py
mcp_feedback_hall/desktop_release/mcp-feedback-enhanced-desktop-linux
mcp_feedback_hall/desktop_release/mcp-feedback-enhanced-desktop-macos-arm64
mcp_feedback_hall/desktop_release/mcp-feedback-enhanced-desktop-macos-intel
mcp_feedback_hall/desktop_release/mcp-feedback-enhanced-desktop.exe
mcp_feedback_hall/utils/__init__.py
mcp_feedback_hall/utils/error_handler.py
mcp_feedback_hall/utils/memory_monitor.py
mcp_feedback_hall/utils/resource_manager.py
mcp_feedback_hall/web/__init__.py
mcp_feedback_hall/web/main.py
mcp_feedback_hall/web/constants/__init__.py
mcp_feedback_hall/web/constants/message_codes.py
mcp_feedback_hall/web/locales/en/translation.json
mcp_feedback_hall/web/locales/zh-CN/translation.json
mcp_feedback_hall/web/locales/zh-TW/translation.json
mcp_feedback_hall/web/models/__init__.py
mcp_feedback_hall/web/models/feedback_result.py
mcp_feedback_hall/web/models/feedback_session.py
mcp_feedback_hall/web/routes/__init__.py
mcp_feedback_hall/web/routes/main_routes.py
mcp_feedback_hall/web/static/favicon.ico
mcp_feedback_hall/web/static/icon-192.png
mcp_feedback_hall/web/static/icon.svg
mcp_feedback_hall/web/static/index.html
mcp_feedback_hall/web/static/css/audio-management.css
mcp_feedback_hall/web/static/css/notification-settings.css
mcp_feedback_hall/web/static/css/prompt-management.css
mcp_feedback_hall/web/static/css/session-management.css
mcp_feedback_hall/web/static/css/styles.css
mcp_feedback_hall/web/static/js/app.js
mcp_feedback_hall/web/static/js/i18n.js
mcp_feedback_hall/web/static/js/modules/connection-monitor.js
mcp_feedback_hall/web/static/js/modules/file-upload-manager.js
mcp_feedback_hall/web/static/js/modules/image-handler.js
mcp_feedback_hall-2.7.9.dist-info/METADATA
mcp_feedback_hall-2.7.9.dist-info/WHEEL
mcp_feedback_hall-2.7.9.dist-info/entry_points.txt
mcp_feedback_hall-2.7.9.dist-info/licenses/LICENSE
mcp_feedback_hall-2.7.9.dist-info/RECORD
